{
  "id": "property-ZM3",
  "title": "Beautiful Beachfront 5 Bed Luxury Villa in Plai Laem",
    "description": "- 5 Bedroom, 6 bathroom luxury oceanfront villa\n- Elevated position with private gated beach access\n- Situated in the exclusive Bayside beachfront estate\n- 3 storey contemporary architecture\n- Stunning ocean views from all rooms\n- Fully furnished to an exceptional level\n- High-quality of finishing throughout\n- Infinity-edge oceanfront private pool\n- Expansive covered terrace area\n- Travertine stone tiling throughout outside terraces \n- Outdoor Sala seating & BBQ area\n- Sumptuous materials & design\n- Indoor and outdoor dining areas\n- Open-plan living/dining/kitchen \n- Fully-equipped designer kitchen\n- Brand name built-in appliances\n- Separate laundry room\n- Solar panels to reduce electricity costs\n- Separate staff kitchen and maids room with en-suite \n- Fully managed & maid service\n- Built in air-conditioning\n- Ceiling fans in all rooms\n- Private garage for 2 cars\n- Land: 1000 sqm approx.\n- Villa: 800 sqm approx\n- Freehold tenure\n- Chanote land title",
    "price": 125000000,
    "type": null,
    "bedrooms": null,
    "bathrooms": null,
    "location": {
      "city": "Koh Samui",
      "country": "Thailand",
      "area": "Plai Laem"
  },
  "features": [
    "Sea View"
  ],
  "images": [
    "https://res.cloudinary.com/dhxriuzu5/image/upload/v1749983386/ZM3_Villa-Maliya_cover_1_Large_p5zezs.jpg",
    "https://res.cloudinary.com/dhxriuzu5/image/upload/v1749983390/ZM3-Villa-Maliya-2_Large_va9mds.jpg",
    "https://res.cloudinary.com/dhxriuzu5/image/upload/v1749983390/ZM3-Villa-Maliya-3_Large_rdhvew.jpg",
    "https://res.cloudinary.com/dhxriuzu5/image/upload/v1749983385/ZM3-Villa-Maliya-4_Large_kgwqcv.jpg",
    "https://res.cloudinary.com/dhxriuzu5/image/upload/v1749983383/ZM3_Villa-Maliya-5_Large_qc49vv.jpg",
    "https://res.cloudinary.com/dhxriuzu5/image/upload/v1749983388/ZM3-Villa-Maliya-6_Large_cpsh6v.jpg",
    "https://res.cloudinary.com/dhxriuzu5/image/upload/v1749983385/ZM3-Villa-Maliya-7_Large_izynwa.jpg",
    "https://res.cloudinary.com/dhxriuzu5/image/upload/v1749983388/ZM3-Villa-Maliya-8_Large_mba7b4.jpg",
    "https://res.cloudinary.com/dhxriuzu5/image/upload/v1749983384/ZM3-Villa-Maliya-9_Large_knk2gz.jpg",
    "https://res.cloudinary.com/dhxriuzu5/image/upload/v1749983385/ZM3-Villa-Maliya-10_Large_wegwnw.jpg"
  ],
  "featured": true,
  "newProperty": false,
  "active": true
} 